excel_sandbox/__init__.py
excel_sandbox/pandas_sandbox.py
excel_sandbox/server.py
fetus_mcp_server_excel-0.0.5.dist-info/licenses/LICENSE
fetus_mcp_server_excel-0.0.5.dist-info/METADATA
fetus_mcp_server_excel-0.0.5.dist-info/WHEEL
fetus_mcp_server_excel-0.0.5.dist-info/entry_points.txt
fetus_mcp_server_excel-0.0.5.dist-info/top_level.txt
fetus_mcp_server_excel-0.0.5.dist-info/RECORD
