Metadata-Version: 2.4
Name: fetus-mcp-server-excel
Version: 0.0.5
Summary: Add your description here
Requires-Python: >=3.12
License-File: LICENSE
Requires-Dist: matplotlib>=3.10.3
Requires-Dist: mcp[cli]>=1.9.4
Requires-Dist: numpy>=2.3.0
Requires-Dist: openpyxl>=3.1.5
Requires-Dist: pandas>=2.3.0
Requires-Dist: requests>=2.32.4
Requires-Dist: seaborn>=0.13.2
Dynamic: license-file
